plotnine/__init__.py
plotnine/animation.py
plotnine/doctools.py
plotnine/exceptions.py
plotnine/ggplot.py
plotnine/iapi.py
plotnine/labels.py
plotnine/layer.py
plotnine/options.py
plotnine/py.typed
plotnine/qplot.py
plotnine/typing.py
plotnine/watermark.py
plotnine/_mpl/__init__.py
plotnine/_mpl/_plot_side_space.py
plotnine/_mpl/_plotnine_tight_layout.py
plotnine/_mpl/layout_engine.py
plotnine/_mpl/offsetbox.py
plotnine/_mpl/patches.py
plotnine/_mpl/text.py
plotnine/_mpl/ticker.py
plotnine/_mpl/transforms.py
plotnine/_mpl/utils.py
plotnine/_utils/__init__.py
plotnine/_utils/context.py
plotnine/_utils/dev.py
plotnine/_utils/ipython.py
plotnine/_utils/quarto.py
plotnine/_utils/registry.py
plotnine/coords/__init__.py
plotnine/coords/coord.py
plotnine/coords/coord_cartesian.py
plotnine/coords/coord_fixed.py
plotnine/coords/coord_flip.py
plotnine/coords/coord_trans.py
plotnine/data/__init__.py
plotnine/data/diamonds.csv
plotnine/data/economics.csv
plotnine/data/economics_long.csv
plotnine/data/faithful.csv
plotnine/data/faithfuld.csv
plotnine/data/huron.csv
plotnine/data/luv_colours.csv
plotnine/data/meat.csv
plotnine/data/midwest.csv
plotnine/data/mpg.csv
plotnine/data/msleep.csv
plotnine/data/mtcars.csv
plotnine/data/pageviews.csv
plotnine/data/penguins.csv
plotnine/data/presidential.csv
plotnine/data/seals.csv
plotnine/data/txhousing.csv
plotnine/facets/__init__.py
plotnine/facets/facet.py
plotnine/facets/facet_grid.py
plotnine/facets/facet_null.py
plotnine/facets/facet_wrap.py
plotnine/facets/labelling.py
plotnine/facets/layout.py
plotnine/facets/strips.py
plotnine/geoms/__init__.py
plotnine/geoms/annotate.py
plotnine/geoms/annotation_logticks.py
plotnine/geoms/annotation_stripes.py
plotnine/geoms/geom.py
plotnine/geoms/geom_abline.py
plotnine/geoms/geom_area.py
plotnine/geoms/geom_bar.py
plotnine/geoms/geom_bin_2d.py
plotnine/geoms/geom_blank.py
plotnine/geoms/geom_boxplot.py
plotnine/geoms/geom_col.py
plotnine/geoms/geom_count.py
plotnine/geoms/geom_crossbar.py
plotnine-0.14.6.dist-info/licenses/LICENSE
plotnine-0.14.6.dist-info/METADATA
plotnine-0.14.6.dist-info/WHEEL
plotnine-0.14.6.dist-info/top_level.txt
plotnine-0.14.6.dist-info/RECORD
