Metadata-Version: 2.4
Name: plotnine
Version: 0.14.6
Summary: A Grammar of Graphics for Python
Author-email: Hassan Kibirige <has2k1@gmail.com>
License: The MIT License (MIT)
Project-URL: homepage, https://plotnine.readthedocs.io/en/stable
Project-URL: repository, https://github.com/has2k1/plotnine
Project-URL: changelog, https://plotnine.readthedocs.io/en/stable/changelog.html
Project-URL: ci, https://github.com/has2k1/plotnine/actions
Classifier: Intended Audience :: Science/Research
Classifier: License :: OSI Approved :: MIT License
Classifier: Operating System :: Microsoft :: Windows
Classifier: Operating System :: Unix
Classifier: Operating System :: MacOS
Classifier: Programming Language :: Python :: 3 :: Only
Classifier: Programming Language :: Python :: 3.10
Classifier: Programming Language :: Python :: 3.11
Classifier: Programming Language :: Python :: 3.12
Classifier: Programming Language :: Python :: 3.13
Classifier: Framework :: Matplotlib
Classifier: Topic :: Scientific/Engineering :: Visualization
Requires-Python: >=3.10
License-File: LICENSE
Requires-Dist: matplotlib>=3.8.0
Requires-Dist: pandas>=2.2.0
Requires-Dist: mizani~=0.13.0
Requires-Dist: numpy>=1.23.5
Requires-Dist: scipy<1.16.0,>=1.8.0
Requires-Dist: statsmodels>=0.14.0
Provides-Extra: all
Requires-Dist: plotnine[extra]; extra == "all"
Requires-Dist: plotnine[doc]; extra == "all"
Requires-Dist: plotnine[lint]; extra == "all"
Requires-Dist: plotnine[test]; extra == "all"
Requires-Dist: plotnine[build]; extra == "all"
Requires-Dist: plotnine[dev]; extra == "all"
Provides-Extra: extra
Requires-Dist: adjustText>=1.2.0; extra == "extra"
Requires-Dist: geopandas>=1.0.0; extra == "extra"
Requires-Dist: scikit-learn>1.2.0; extra == "extra"
Requires-Dist: scikit-misc>=0.5.1; extra == "extra"
Provides-Extra: doc
Requires-Dist: jupyter; extra == "doc"
Requires-Dist: nbsphinx; extra == "doc"
Requires-Dist: click; extra == "doc"
Requires-Dist: numpydoc>=0.9.1; extra == "doc"
Requires-Dist: quartodoc>=0.7.2; extra == "doc"
Provides-Extra: lint
Requires-Dist: ruff; extra == "lint"
Provides-Extra: test
Requires-Dist: pytest-cov>=4.0.0; extra == "test"
Provides-Extra: build
Requires-Dist: build; extra == "build"
Requires-Dist: wheel; extra == "build"
Provides-Extra: dev
Requires-Dist: twine; extra == "dev"
Requires-Dist: plotnine[typing]; extra == "dev"
Requires-Dist: pre-commit; extra == "dev"
Provides-Extra: typing
Requires-Dist: pyright==1.1.391; extra == "typing"
Requires-Dist: ipython; extra == "typing"
Requires-Dist: pandas-stubs; extra == "typing"
Dynamic: license-file
